etl_forge/__init__.py
etl_forge/cli.py
etl_forge/exceptions.py
etl_forge/generator.py
etl_forge/schema_adapter.py
etl_forge/validator.py
etl_forge-1.1.0.dist-info/METADATA
etl_forge-1.1.0.dist-info/WHEEL
etl_forge-1.1.0.dist-info/entry_points.txt
etl_forge-1.1.0.dist-info/top_level.txt
etl_forge-1.1.0.dist-info/RECORD
