Metadata-Version: 2.4
Name: etl-forge
Version: 1.1.0
Summary: A Python library for generating synthetic test data and validating ETL outputs for tabular data (pandas DataFrames).
Author-email: Kyriakos Kartas <mail@kkartas.gr>
Project-URL: Homepage, https://github.com/kkartas/ETLForge
Project-URL: Bug Tracker, https://github.com/kkartas/ETLForge/issues
Keywords: etl,testing,data validation,synthetic data,data quality
Classifier: Development Status :: 5 - Production/Stable
Classifier: Intended Audience :: Developers
Classifier: Topic :: Software Development :: Testing
Classifier: License :: OSI Approved :: MIT License
Classifier: Programming Language :: Python :: 3
Classifier: Programming Language :: Python :: 3.9
Classifier: Programming Language :: Python :: 3.10
Classifier: Programming Language :: Python :: 3.11
Requires-Python: >=3.9
Requires-Dist: pandas>=1.3.0
Requires-Dist: pyyaml>=5.4.0
Requires-Dist: click>=8.0.0
Requires-Dist: numpy>=1.21.0
Requires-Dist: psutil>=5.9.0
Provides-Extra: faker
Requires-Dist: faker>=15.0.0; extra == "faker"
Provides-Extra: excel
Requires-Dist: openpyxl>=3.0.0; extra == "excel"
Provides-Extra: dev
Requires-Dist: pytest>=6.0.0; extra == "dev"
Requires-Dist: pytest-cov>=2.0.0; extra == "dev"
Requires-Dist: black>=21.0.0; extra == "dev"
Requires-Dist: flake8>=3.8.0; extra == "dev"
Requires-Dist: mypy>=0.900; extra == "dev"
Requires-Dist: types-PyYAML>=6.0.0; extra == "dev"
Requires-Dist: matplotlib>=3.5.0; extra == "dev"
Requires-Dist: coverage>=6.0; extra == "dev"
Requires-Dist: sphinx>=4.0.0; extra == "dev"
Requires-Dist: sphinx-rtd-theme>=1.0.0; extra == "dev"
Requires-Dist: faker>=15.0.0; extra == "dev"
Requires-Dist: openpyxl>=3.0.0; extra == "dev"
